simpleapi_kkr/__init__.py
simpleapi_kkr/main.py
simpleapi_kkr/request.py
simpleapi_kkr/response.py
simpleapi_kkr-0.1.0.dist-info/METADATA
simpleapi_kkr-0.1.0.dist-info/WHEEL
simpleapi_kkr-0.1.0.dist-info/RECORD
