Metadata-Version: 2.1
Name: simpleapi_kkr
Version: 0.1.0
Summary: 
Author: kalyankr
Author-email: kalyan.katla@gmail.com
Requires-Python: >=3.12,<4.0
Classifier: Programming Language :: Python :: 3
Classifier: Programming Language :: Python :: 3.12
Requires-Dist: gunicorn (>=23.0.0,<24.0.0)
Requires-Dist: parse (>=1.20.2,<2.0.0)
